[
  {
    "id": "semclip-2026",
    "title": "SemCLIP: A semantic memory-aligned vision language model",
    "authors": ["T. Syeda-Mahmood","K.C.L. Wong","S. Kashyap","N. Dsouza","L. Shi","R. Mahmood","H. Wang"],
    "year": 2026,
    "venue": "PMLR / NeurIPS UniReps Workshop",
    "type": "workshop",
    "venue_category": "Workshop",
    "venue_group": "AI/ML/Computer Vision",
    "topics": []
  },
  {
    "id": "hopfield-encoded-reps-2024",
    "title": "Modern Hopfield Networks meet Encoded Neural Representations – Addressing Practical Considerations",
    "authors": ["S. Kashyap","N. Dsouza","L. Shi","K.C.L. Wong","H. Wang","T. Syeda-Mahmood"],
    "year": 2024,
    "venue": "PMLR / NeurIPS UniReps Workshop",
    "type": "workshop",
    "venue_category": "Workshop",
    "venue_group": "AI/ML/Computer Vision",
    "topics": []
  },
  {
    "id": "radiology-similarity-embedding-2022",
    "title": "Searching for Fine-Grained Queries in Radiology Reports Using Similarity-Preserving Contrastive Embedding",
    "authors": ["T. Syeda-Mahmood","L. Shi"],
    "year": 2022,
    "venue": "JMLR",
    "type": "journal",
    "venue_category": "Journal",
    "venue_group": "AI/ML/Computer Vision",
    "topics": []
  },
  {
    "id": "lexicon-annotation-naacl-2022",
    "title": "Improving Neural Models for Radiology Report Retrieval with Lexicon-based Automated Annotation",
    "authors": ["L. Shi","T. Syeda-Mahmood","T. Baldwin"],
    "year": 2022,
    "venue": "NAACL",
    "type": "conference",
    "venue_category": "Conference",
    "venue_group": "AI/ML/Computer Vision",
    "topics": []
  },
  {
    "id": "spatial-flattening-isbi-2022",
    "title": "Spatially preserving flattening for location-aware classification of findings in chest X-rays",
    "authors": ["N. Srivathsa","R. Mahmood","T. Syeda-Mahmood"],
    "year": 2022,
    "venue": "ISBI",
    "type": "conference",
    "venue_category": "Conference",
    "venue_group": "Medical AI/Medical Imaging AI",
    "topics": []
  },
  {
    "id": "taxonomy-kr-1989",
    "title": "Taxonomic Syntax for First Order Inference",
    "authors": ["D. McAllester","R. Givan","S.T. Fathima"],
    "year": 1989,
    "venue": "KR",
    "type": "conference",
    "venue_category": "Conference",
    "venue_group": "AI/ML/Computer Vision",
    "topics": []
  },
  {
    "id": "cvpr-2026-phrase-apo",
    "title": "Phrase-grounded APO for improving chest X-ray report generation",
    "authors": ["R. Mahmood","T. Syeda-Mahmood"],
    "year": 2026,
    "venue": "CVPR",
    "type": "conference",
    "venue_category": "Conference",
    "venue_group": "AI/ML/Computer Vision",
    "topics": []
  },
  {
    "id": "isbi-2026-report-correction",
    "title": "Automatic correction of generative AI chest X-ray radiology reports",
    "authors": ["R. Mahmood","P.K. Yan","T. Syeda-Mahmood"],
    "year": 2026,
    "venue": "ISBI",
    "type": "conference",
    "venue_category": "Conference",
    "venue_group": "Medical AI/Medical Imaging AI",
    "topics": []
  },
  {
    "id": "miccai-fact-checking-2025",
    "title": "Phrase-grounded Fact-checking for Automatically Generated Chest X-ray Reports",
    "authors": ["M. Machado-Reyes","J. Wu","P. Kaviani","K.C.L. Wong","N. Dsouza","M. Kalra","G. Wang","P. Yan","T. Syeda-Mahmood"],
    "year": 2025,
    "venue": "MICCAI",
    "type": "conference",
    "venue_category": "Conference",
    "venue_group": "Medical AI/Medical Imaging AI",
    "topics": []
  },
  {
    "id": "nature-mim-ventricular-2024",
    "title": "Unsupervised ensemble-based phenotyping enhances gene discoverability in imaging genetics: new associations from left-ventricular morphology",
    "authors": ["R. Bonazzola","E. Ferrante","N. Ravikumar","Y. Xia","B. Keavney","S. Plein","T. Syeda-Mahmood","A.F. Frangi"],
    "year": 2024,
    "venue": "Nature Machine Intelligence",
    "type": "journal",
    "venue_category": "Journal",
    "venue_group": "AI/ML/Computer Vision",
    "topics": []
  },
  {
    "id": "medical-ai-medical-image-analysis-2024",
    "title": "Fusing Modalities by Multiplexed Graph Neural Networks for Outcome Prediction from Medical Data",
    "authors": ["N.S. D’Souza","H. Wang","A. Giovannini","A. Foncubierta-Rodríguez","K. Beck","O. Boyko","T. Syeda-Mahmood"],
    "year": 2024,
    "venue": "Medical Image Analysis",
    "type": "journal",
    "venue_category": "Journal",
    "venue_group": "Medical AI/Medical Imaging AI",
    "topics": []
  },
  {
    "id": "digital-twins-npj-2024",
    "title": "Digital twins for health: a scoping review",
    "authors": ["E. Katsoulakis","Q. Wang","H. Wu","L. Shahriyari","R. Fletcher","J. Liu","T. Syeda-Mahmood"],
    "year": 2024,
    "venue": "NPJ Digital Medicine",
    "type": "journal",
    "venue_category": "Journal",
    "venue_group": "Medical AI/Medical Imaging AI",
    "topics": []
  },
  {
    "id": "cnn-pet-mri-lymphoma-2026",
    "title": "CNN-based detection of pediatric lymphoma on whole body 18F-FDG PET/MRI",
    "authors": ["S. Singh","Y.U. Lokesha","H. Wang","M.J. Barrow","R. Von Kruechten","I. Vasyliv","A.H. Sarrami","J.T.Y. Wu","L. Baratto","L.C. Adams","H.G. Kim","J. Wong","T. Liang","S. Gatidis","T. Syeda-Mahmood","H.E. Daldrup-Link"],
    "year": 2026,
    "venue": "American Journal of Nuclear Medicine and Molecular Imaging",
    "type": "journal",
    "venue_category": "Journal",
    "venue_group": "Medical AI/Medical Imaging AI",
    "topics": []
  },
  {
    "id": "hnotseg-xs-tmi-2026",
    "title": "HNOSeg-XS: Extremely Small Hartley Neural Operator for Efficient and Resolution-Robust 3D Image Segmentation",
    "authors": ["K.C.L. Wong","H. Wang","T. Syeda-Mahmood"],
    "year": 2026,
    "venue": "IEEE Transactions on Medical Imaging",
    "type": "journal",
    "venue_category": "Journal",
    "venue_group": "Medical AI/Medical Imaging AI",
    "topics": []
  },
  {
    "id": "ijcv-survey-multimodal-2024",
    "title": "Multimodal Machine Learning in Image-Based and Clinical Biomedicine: Survey and Prospects",
    "authors": ["E. Warner","J. Lee","W. Hsu","T. Syeda-Mahmood","C.E. Kahn","O. Gevaert","A. Rao"],
    "year": 2024,
    "venue": "International Journal of Computer Vision",
    "type": "journal",
    "venue_category": "Journal",
    "venue_group": "AI/ML/Computer Vision",
    "topics": []
  },
  {
    "id": "ai-vs-radiologists-jamia-2020",
    "title": "Artificial Intelligence versus Entry-level Radiologists for Full-fledged Preliminary Read of Frontal AP Chest Radiographs: A Comparative Study",
    "authors": ["J. Wu","K.C.L. Wong","Y. Gur","N. Ansari","A. Karargyris","A. Sharma","M. Morris","B. Sabury","H. Ahmad","O. Boyko","A. Syed","A. Jadhav","H. Wang","A. Pillai","S. Kashyap","M. Moradi","T. Syeda-Mahmood"],
    "year": 2020,
    "venue": "JAMIA",
    "type": "journal",
    "venue_category": "Journal",
    "venue_group": "Medical AI/Medical Imaging AI",
    "topics": []
  },
  {
    "id": "digital-twins-frontiers-2022",
    "title": "Exploring approaches for predictive cancer patient digital twins: Opportunities for collaboration and innovation",
    "authors": [
      "E. Stahlberg",
      "M. Abdel-Rahman",
      "B. Aguilar",
      "A. Asadpoure",
      "R. Beckman",
      "L. Borkon",
      "J. Bryan",
      "C.M. Cebulla",
      "Y.H. Chang",
      "A. Chatterjee",
      "J. Deng"
    ],
    "year": 2022,
    "venue": "Frontiers in Digital Health",
    "type": "journal",
    "venue_category": "Journal",
    "venue_group": "Medical AI/Medical Imaging AI",
    "topics": []
  },
  {
    "id": "nature-medicine-digital-twins-2021",
    "title": "Digital twins for predictive oncology will be a paradigm shift for precision cancer care",
    "authors": [
      "T. Hernandez-Boussard",
      "P. Macklin",
      "E.J. Greenspan",
      "A.L. Gryshuk",
      "E. Stahlberg",
      "T. Syeda-Mahmood",
      "I. Shmulevich"
    ],
    "year": 2021,
    "venue": "Nature Medicine",
    "type": "journal",
    "venue_category": "Journal",
    "venue_group": "Medical AI/Medical Imaging AI",
    "topics": []
  },
  {
    "id": "jacr-bigdata-radiology-2018",
    "title": "Role of Big Data and Machine Learning in Diagnostic Decision Support in Radiology",
    "authors": ["T. Syeda-Mahmood"],
    "year": 2018,
    "venue": "Journal of the American College of Radiology",
    "type": "journal",
    "venue_category": "Journal",
    "venue_group": "Medical AI/Medical Imaging AI",
    "topics": []
  },
  {
    "id": "medical-image-analysis-2018-unbalanced-data",
    "title": "Building medical image classifiers with very unbalanced and limited data using segmentation networks",
    "authors": ["K.C.L. Wong", "T. Syeda-Mahmood", "M. Moradi"],
    "year": 2018,
    "venue": "Medical Image Analysis",
    "type": "journal",
    "venue_category": "Journal",
    "venue_group": "Medical AI/Medical Imaging AI",
    "topics": []
  },
  {
    "id": "fast-anatomy-segmentation-2018",
    "title": "Fast Anatomy Segmentation by Combining Coarse Scale Multi-Atlas Label Fusion with Fine Scale Corrective Learning",
    "authors": ["H. Wang", "D. Kakrania", "H. Tang", "P. Prasanna", "T. Syeda-Mahmood"],
    "year": 2018,
    "venue": "Computerized Medical Imaging and Graphics",
    "type": "journal",
    "venue_category": "Journal",
    "venue_group": "Medical AI/Medical Imaging AI",
    "topics": []
  },
  {
    "id": "clapss-neurocomputing-2013",
    "title": "Complex Local Phase based Subjective Surfaces (CLAPSS) and its Application to DIC Red Blood Cell Image Segmentation",
    "authors": [
      "T. Chen",
      "Y. Zhang",
      "C. Wang",
      "Z. Qu",
      "F. Wang",
      "T. Syeda-Mahmood"
    ],
    "year": 2013,
    "venue": "Neurocomputing",
    "type": "journal",
    "venue_category": "Journal",
    "venue_group": "AI/ML/Computer Vision",
    "topics": []
  },
  {
    "id": "event-detection-cviu-2004",
    "title": "Event Detection in Video",
    "authors": [
      "T. Syeda-Mahmood",
      "I. Haritaoglu",
      "T. Huang"
    ],
    "year": 2004,
    "venue": "Computer Vision and Image Understanding",
    "type": "journal",
    "venue_category": "Journal",
    "venue_group": "AI/ML/Computer Vision",
    "topics": []
  },
  {
    "id": "federated-data-warehousing-2002",
    "title": "Accessing and mining federated data sources in Database Warehousing Institute Journal",
    "authors": ["T. Syeda-Mahmood", "B. Kelkar"],
    "year": 2002,
    "venue": "Database Warehousing Institute Journal",
    "type": "journal",
    "venue_category": "Journal",
    "venue_group": "Other",
    "topics": []
  },
  {
    "id": "netview-multimedia-2001",
    "title": "NetView: Integrating large-scale distributed visual databases",
    "authors": ["A. Zhang", "W. Chang", "T. Syeda-Mahmood"],
    "year": 2001,
    "venue": "Morgan Kaufmann",
    "type": "book",
    "venue_category": "Book",
    "venue_group": "AI/ML/Computer Vision",
    "topics": []
  },
  {
    "id": "color-shape-visual-comms-2000",
    "title": "On describing color and shape information in images",
    "authors": ["T. Syeda-Mahmood", "D. Petkovic"],
    "year": 2000,
    "venue": "Journal of Visual Communication",
    "type": "journal",
    "venue_category": "Journal",
    "venue_group": "AI/ML/Computer Vision",
    "topics": []
  },
  {
    "id": "cviu-salient-texture-1999",
    "title": "Detection of salient texture regions in images",
    "authors": ["T. Syeda-Mahmood"],
    "year": 1999,
    "venue": "Computer Vision and Image Understanding",
    "type": "journal",
    "venue_category": "Journal",
    "venue_group": "AI/ML/Computer Vision",
    "topics": []
  },
  {
    "id": "ieee-tpami-line-drawings-1999",
    "title": "Indexing of Technical Line Drawing Databases",
    "authors": ["T. Syeda-Mahmood"],
    "year": 1999,
    "venue": "IEEE Transactions on Pattern Analysis and Machine Intelligence",
    "type": "journal",
    "venue_category": "Journal",
    "venue_group": "AI/ML/Computer Vision",
    "topics": []
  },
  {
    "id": "ieee-multimedia-netview-1998",
    "title": "NetView: Integrating large-scale distributed visual databases",
    "authors": ["W. Chang", "D. Murthy", "A. Zhang", "T. Syeda-Mahmood"],
    "year": 1998,
    "venue": "IEEE Multimedia",
    "type": "journal",
    "venue_category": "Journal",
    "venue_group": "AI/ML/Computer Vision",
    "topics": []
  },
  {
    "id": "acm-mm-resource-selection-1997",
    "title": "Efficient Resource Selection in Distributed Visual Information Systems",
    "authors": ["W. Chang", "G. Sheikholeslami", "A. Zhang", "T. Syeda-Mahmood"],
    "year": 1997,
    "venue": "ACM Multimedia",
    "type": "conference",
    "venue_category": "Conference",
    "venue_group": "AI/ML/Computer Vision",
    "topics": []
  },
  {
    "id": "multimedia-tools-retrieval-1997",
    "title": "Supporting Content-Based Retrieval in Large Image Database Systems",
    "authors": ["E. Remias", "G. Sheikholeslami", "A. Zhang", "T. Syeda-Mahmood"],
    "year": 1997,
    "venue": "Multimedia Tools and Applications",
    "type": "journal",
    "venue_category": "Journal",
    "venue_group": "AI/ML/Computer Vision",
    "topics": []
  },
  {
    "id": "query-localization-1997",
    "title": "Query localization using nona-tree in very large databases",
    "authors": ["A. Zhang", "R. Acharya", "T. Syeda-Mahmood"],
    "year": 1997,
    "venue": "Multimedia Tools and Applications",
    "type": "journal",
    "venue_category": "Journal",
    "venue_group": "AI/ML/Computer Vision",
    "topics": []
  },
  {
    "id": "ijcv-color-model-driven-1997",
    "title": "Data and model-driven selection using color regions",
    "authors": ["T. Syeda-Mahmood"],
    "year": 1997,
    "venue": "International Journal of Computer Vision",
    "type": "journal",
    "venue_category": "Journal",
    "venue_group": "AI/ML/Computer Vision",
    "topics": []
  },
  {
    "id": "cviu-parallel-line-1997",
    "title": "Data and model-driven selection using parallel-line groups",
    "authors": ["T. Syeda-Mahmood"],
    "year": 1997,
    "venue": "Computer Vision and Image Understanding",
    "type": "journal",
    "venue_category": "Journal",
    "venue_group": "AI/ML/Computer Vision",
    "topics": []
  },
  {
    "id": "maximum-entropy-interpolation-1990",
    "title": "A Maximum Entropy Approach to Interpolation",
    "authors": ["S.T. Fathima", "B. Yegnanarayana"],
    "year": 1990,
    "venue": "Signal Processing",
    "type": "journal",
    "venue_category": "Journal",
    "venue_group": "Other",
    "topics": []
  },
  {
    "id": "ieee-aspp-interpolation-1989",
    "title": "Significance of Initial Interpolation in Band-limited Signal Interpolation",
    "authors": [
      "B. Yegnanarayana",
      "S.T. Fathima",
      "B.T.K.R. Nehru",
      "B. Venkatramanan"
    ],
    "year": 1989,
    "venue": "IEEE Transactions on Acoustics, Speech, and Signal Processing",
    "type": "journal",
    "venue_category": "Journal",
    "venue_group": "Other",
    "topics": []
  },
  {
    "id": "signal-processing-interpolation-1988",
    "title": "A Noise Canceling Approach to Signal Interpolation",
    "authors": ["S.T. Fathima"],
    "year": 1988,
    "venue": "Signal Processing IV: Theories and Applications",
    "type": "book",
    "venue_category": "Book",
    "venue_group": "Other",
    "topics": []
  },
  {
    "id": "foundation-models-healthcare-springer-2026",
    "title": "Foundation Models for Healthcare",
    "authors": ["T. F. Syeda-Mahmood"],
    "year": 2026,
    "venue": "Springer",
    "type": "book",
    "venue_category": "Book",
    "venue_group": "Medical AI/Medical Imaging AI",
    "topics": []
  },
  {
    "id": "deep-learning-medical-imaging-springer-lncs-2018",
    "title": "Deep Learning in Medical Image Analysis and Multimodal Learning for Clinical Decision Support",
    "authors": ["D. Stoyanov", "T. F. Syeda-Mahmood"],
    "year": 2018,
    "venue": "Springer LNCS",
    "type": "book",
    "venue_category": "Book",
    "venue_group": "Medical AI/Medical Imaging AI",
    "topics": [],
    "metadata": {
      "url": "https://www.springer.com/us/book/9783030008888"
    }
  },
  {
    "id": "biomedical-image-processing-greenspan-2010",
    "title": "Image region segmentation using statistical models",
    "authors": ["H. Greenspan", "T. F. Syeda-Mahmood"],
    "year": 2010,
    "venue": "Springer",
    "type": "book",
    "venue_category": "Book",
    "venue_group": "Medical AI/Medical Imaging AI",
    "topics": []
  },
  {
    "id": "medical-content-retrieval-lncs-5853-2009",
    "title": "Medical Content-based Retrieval for Clinical Decision Support",
    "authors": ["B. Caputo", "H. Muller", "T. F. Syeda-Mahmood", "F. Wang", "J. Duncan"],
    "year": 2009,
    "venue": "Springer LNCS 5853",
    "type": "book",
    "venue_category": "Book",
    "venue_group": "Medical AI/Medical Imaging AI",
    "topics": []
  },
  {
    "id": "semantic-web-processes-2006",
    "title": "Matching and Mapping for Semantic Web Processes",
    "authors": ["T. Syeda-Mahmood", "R. Goodwin", "R. Akkiraju", "A. Ivan"],
    "year": 2006,
    "venue": "Springer",
    "type": "book",
    "venue_category": "Book",
    "venue_group": "AI/ML/Computer Vision",
    "topics": []
  },
  {
    "id": "central-venous-catheters-miccai-2019",
    "title": "Automated detection and type classification of central venous catheters in chest X-rays",
    "authors": ["V. Subramanian", "H. Wang", "J. Wu", "K.C.L. Wong", "A. Sharma", "T. Syeda-Mahmood"],
    "year": 2019,
    "venue": "MICCAI",
    "type": "conference",
    "venue_category": "Conference",
    "venue_group": "Medical AI/Medical Imaging AI",
    "topics": []
  },
  {
    "id": "bimodal-annotation-miccai-2018",
    "title": "Bimodal network architectures for automatic generation of image annotation from text",
    "authors": ["M. Moradi", "A. Madani", "Y. Guy", "Y. Guo", "T. Syeda-Mahmood"],
    "year": 2018,
    "venue": "MICCAI",
    "type": "conference",
    "venue_category": "Conference",
    "venue_group": "Medical AI/Medical Imaging AI",
    "topics": []
  },
  {
    "id": "exponential-log-loss-miccai-2018",
    "title": "3D Segmentation with Exponential Logarithmic Loss for Highly Unbalanced Object Sizes",
    "authors": ["K.C.L. Wong", "M. Moradi", "H. Tang", "T. Syeda-Mahmood"],
    "year": 2018,
    "venue": "MICCAI",
    "type": "conference",
    "venue_category": "Conference",
    "venue_group": "Medical AI/Medical Imaging AI",
    "topics": []
  },
  {
    "id": "roi-multiatlas-miccai-2017",
    "title": "A Multi-Atlas Approach to Region of Interest Detection for Medical Image Classification",
    "authors": ["H. Wang", "M. Moradi", "Y. Gur", "P. Prasanna", "T. Syeda-Mahmood"],
    "year": 2017,
    "venue": "MICCAI",
    "type": "conference",
    "venue_category": "Conference",
    "venue_group": "Medical AI/Medical Imaging AI",
    "topics": []
  },
  {
    "id": "small-sample-disease-detection-miccai-2017",
    "title": "Building Disease Detection Algorithms with Very Small Number of Positive Samples",
    "authors": ["K.C.L. Wong", "M. Moradi", "A. Karargyris", "T. Syeda-Mahmood"],
    "year": 2017,
    "venue": "MICCAI",
    "type": "conference",
    "venue_category": "Conference",
    "venue_group": "Medical AI/Medical Imaging AI",
    "topics": []
  },
  {
    "id": "aortic-stenosis-risk-miccai-2016",
    "title": "Identifying Patients at Risk for Aortic Stenosis Through Learning from Multimodal Data",
    "authors": ["T. Syeda-Mahmood", "Y. Guo", "M. Moradi", "D. Beymer", "D. Rajan", "Y. Cao", "Y. Gur", "M. Negahdar"],
    "year": 2016,
    "venue": "MICCAI",
    "type": "conference",
    "venue_category": "Conference",
    "venue_group": "Medical AI/Medical Imaging AI",
    "topics": []
  },
  {
    "id": "cross-modality-transform-miccai-2016",
    "title": "A Cross-Modality Neural Network Transform for Semi-automatic Medical Image Annotation",
    "authors": ["M. Moradi", "Y. Guo", "Y. Gur", "M. Negahdar", "T. Syeda-Mahmood"],
    "year": 2016,
    "venue": "MICCAI",
    "type": "conference",
    "venue_category": "Conference",
    "venue_group": "Medical AI/Medical Imaging AI",
    "topics": []
  },
  {
    "id": "groupwise-shape-registration-miccai-2009",
    "title": "Closed-form Jensen-Rényi Divergence for Mixture of Gaussians & Applications to Group-wise Shape Registration",
    "authors": ["F. Wang", "T. Syeda-Mahmood", "B.C. Vemuri", "D. Beymer", "A. Rangarajan"],
    "year": 2009,
    "venue": "MICCAI",
    "type": "conference",
    "venue_category": "Conference",
    "venue_group": "Medical AI/Medical Imaging AI",
    "topics": []
  },
  {
    "id": "cardiac-echo-miccai-2007",
    "title": "Characterizing spatio-temporal patterns for disease discrimination in cardiac echo videos",
    "authors": ["T. Syeda-Mahmood", "F. Wang", "D. Beymer", "M. London", "R. Reddy"],
    "year": 2007,
    "venue": "MICCAI",
    "type": "conference",
    "venue_category": "Conference",
    "venue_group": "Medical AI/Medical Imaging AI",
    "topics": []
  },
  {
    "id": "cerebral-aneurysm-outcome-amia-2022",
    "title": "Towards Automatic Prediction of Outcome in Treatment of Cerebral Aneurysms",
    "authors": ["A. Jadhav", "M. Moradi", "S. Kashyap", "T. Syeda-Mahmood"],
    "year": 2022,
    "venue": "AMIA Annual Symposium",
    "type": "conference",
    "venue_category": "Conference",
    "venue_group": "Medical AI/Medical Imaging AI",
    "topics": []
  },
  {
    "id": "semantic-expansion-clinical-preferences-amia-2021",
    "title": "Semantic Expansion of Clinician Generated Data Preferences for Automatic Patient Data Summarization",
    "authors": ["A. Jadhav", "T. Baldwin", "J. Wu", "V. Mukherjee", "T. Syeda-Mahmood"],
    "year": 2021,
    "venue": "AMIA Annual Symposium",
    "type": "conference",
    "venue_category": "Conference",
    "venue_group": "Medical AI/Medical Imaging AI",
    "topics": []
  },
  {
    "id": "dilated-cardiomyopathy-amia-2014",
    "title": "Automatic detection of dilated cardiomyopathy in cardiac ultrasound videos",
    "authors": ["R. Mahmood", "Q. Wang", "T. Syeda-Mahmood"],
    "year": 2014,
    "venue": "AMIA Annual Symposium",
    "type": "conference",
    "venue_category": "Conference",
    "venue_group": "Medical AI/Medical Imaging AI",
    "topics": []
  },
  {
    "id": "echocardiography-workflows-amia-2013",
    "title": "Mining Echocardiography Workflows for Disease Discriminative Patterns",
    "authors": ["R. Kumar", "K.C.L. Vemuri", "F. Wang", "T. Syeda-Mahmood", "C. Brannon"],
    "year": 2013,
    "venue": "AMIA Annual Symposium",
    "type": "conference",
    "venue_category": "Conference",
    "venue_group": "Medical AI/Medical Imaging AI",
    "topics": []
  },
  {
    "id": "multimodal-clinical-decision-platform-amia-2012",
    "title": "Multimodal Informatics Platform for Clinical Decision Support",
    "authors": ["T. Syeda-Mahmood", "D. Beymer", "F. Wang", "R. Kumar", "Y. Zhang"],
    "year": 2012,
    "venue": "AMIA Annual Symposium",
    "type": "conference",
    "venue_category": "Conference",
    "venue_group": "Medical AI/Medical Imaging AI",
    "topics": []
  },
  {
    "id": "ipmi-dw-mri-hyperspherical-2009",
    "title": "Multi-fiber Reconstruction from DW-MRI data using a Continuous Mixture of Hyperspherical von Mises-Fisher Distributions",
    "authors": ["R. Kumar", "B.C. Vemuri", "F. Wang", "T. Syeda-Mahmood", "P.R. Carney", "T.H. Mareci"],
    "year": 2009,
    "venue": "IPMI",
    "type": "conference",
    "venue_category": "Conference",
    "venue_group": "Medical AI/Medical Imaging AI",
    "topics": []
  },
  {
    "id": "cvpr-chest-xray-apo-2026",
    "title": "Phrase-grounded APO for Improving Chest X-ray Report Generation",
    "authors": ["R. Mahmood", "T. Syeda-Mahmood"],
    "year": 2026,
    "venue": "CVPR",
    "type": "conference",
    "venue_category": "Conference",
    "venue_group": "AI/ML/Computer Vision",
    "topics": []
  },
  {
    "id": "aaai-clinical-concept-extraction-2017",
    "title": "Efficient Clinical Concept Extraction in Electronic Medical Records",
    "authors": ["Y. Guo", "D. Kakrania", "T. Baldwin", "T. Syeda-Mahmood"],
    "year": 2017,
    "venue": "AAAI",
    "type": "conference",
    "venue_category": "Conference",
    "venue_group": "AI/ML/Computer Vision",
    "topics": []
  },
  {
    "id": "ipcr-echocardiogram-segmentation-2014",
    "title": "Segmentation of Anatomical Structures in Four-Chamber View Echocardiogram Images",
    "authors": ["Y. Cao", "T. Syeda-Mahmood", "P. McNeillie"],
    "year": 2014,
    "venue": "ICPR",
    "type": "conference",
    "venue_category": "Conference",
    "venue_group": "Medical AI/Medical Imaging AI",
    "topics": []
  },
  {
    "id": "iccv-heart-sounds-eccv-2008",
    "title": "Shape-similarity-based retrieval of Doppler images for clinical decision support",
    "authors": ["T. Syeda-Mahmood", "P. Turaga", "D. Beymer", "F. Wang", "A. Amir", "H. Greenspan", "K. Pohl"],
    "year": 2010,
    "venue": "CVPR (accepted)",
    "type": "conference",
    "venue_category": "Conference",
    "venue_group": "Medical AI/Medical Imaging AI",
    "topics": []
  },
  {
    "id": "icpr-heart-sound-matching-2008",
    "title": "Shape-based Matching of Heart Sounds",
    "authors": ["T. Syeda-Mahmood", "F. Wang"],
    "year": 2008,
    "venue": "ICPR",
    "type": "conference",
    "venue_category": "Conference",
    "venue_group": "Medical AI/Medical Imaging AI",
    "topics": []
  },
  {
    "id": "acm-mm-video-retrieval-2006",
    "title": "Personalized Concept-Based Multimedia Health Records: Opportunities and Challenges",
    "authors": ["S. Ebadollahi", "T. Syeda-Mahmood", "A. Amir", "A. Coden"],
    "year": 2006,
    "venue": "ACM Multimedia",
    "type": "conference",
    "venue_category": "Conference",
    "venue_group": "AI/ML/Computer Vision",
    "topics": []
  },
  {
    "id": "iccv-formpad-2005",
    "title": "FormPad: A camera-assisted digital notepad",
    "authors": ["T. Syeda-Mahmood", "T. Zimmerman"],
    "year": 2005,
    "venue": "ICCV Demo",
    "type": "conference",
    "venue_category": "Conference",
    "venue_group": "AI/ML/Computer Vision",
    "topics": []
  },
  {
    "id": "icws-semantic-search-2005",
    "title": "Searching Service Repositories by Combining Semantic and Ontological Matching",
    "authors": ["T. Syeda-Mahmood"],
    "year": 2005,
    "venue": "IEEE International Conference on Web Services",
    "type": "conference",
    "venue_category": "Conference",
    "venue_group": "AI/ML/Computer Vision",
    "topics": []
  }

]